{
  "groups": [
    {
      "name": "website.security",
      "type": "com.sfsctech.security.properties.SecurityProperties",
      "sourceType": "com.sfsctech.security.properties.SecurityProperties"
    },
    {
      "name": "website.security.csrf",
      "type": "com.sfsctech.security.properties.SecurityProperties$Csrf",
      "sourceType": "com.sfsctech.security.properties.SecurityProperties",
      "sourceMethod": "getCsrf()"
    },
    {
      "name": "website.security.ddos",
      "type": "com.sfsctech.security.properties.SecurityProperties$Ddos",
      "sourceType": "com.sfsctech.security.properties.SecurityProperties",
      "sourceMethod": "getDdos()"
    }
  ],
  "properties": [
    {
      "name": "website.security.open-xss",
      "type": "java.lang.Boolean",
      "description": "是否打开XSS防御（默认true）",
      "sourceType": "com.sfsctech.security.properties.SecurityProperties"
    },
    {
      "name": "website.security.open-csrf",
      "type": "java.lang.Boolean",
      "description": "是否打开CSRF防御（默认false）",
      "sourceType": "com.sfsctech.security.properties.SecurityProperties"
    },
    {
      "name": "website.security.open-ddoc",
      "type": "java.lang.Boolean",
      "description": "是否打开DDOC防御（默认false）",
      "sourceType": "com.sfsctech.security.properties.SecurityProperties"
    },
    {
      "name": "website.security.csrf.keep-pattern",
      "type": "java.lang.String",
      "description": "CSRF防御Token保持方式，为空默认HttpSession",
      "sourceType": "com.sfsctech.security.properties.SecurityProperties$Csrf"
    },
    {
      "name": "website.security.csrf.intercept-exclude-path",
      "type": "java.util.Set<java.lang.String>",
      "description": "CSRF防御拦截排除路径",
      "sourceType": "com.sfsctech.security.properties.SecurityProperties$Csrf"
    },
    {
      "name": "website.security.csrf.verify-exclude-path",
      "type": "java.util.Set<java.lang.String>",
      "description": "CSRF防御校验排除路径",
      "sourceType": "com.sfsctech.security.properties.SecurityProperties$Csrf"
    },
    {
      "name": "website.security.csrf.required-verify-path",
      "type": "java.util.Set<java.lang.String>",
      "description": "必须通过CSRF防御校验路径",
      "sourceType": "com.sfsctech.security.properties.SecurityProperties$Csrf"
    },
    {
      "name": "website.security.ddos.access-control-allow-origin",
      "type": "java.util.Set<java.lang.String>",
      "description": "跨域请求白名单",
      "sourceType": "com.sfsctech.security.properties.SecurityProperties$Ddos"
    }
  ],
  "hints": [
    {
      "name": "website.security.csrf.keep-pattern",
      "values": [
        {
          "value": "soa",
          "description": "通过分布式服务保持Token"
        },
        {
          "value": "cache",
          "description": "通过缓存服务保持Token"
        }
      ]
    }
  ]
}